pyappframework/README.md
pyappframework/__init__.py
pyappframework/decorators.py
pyappframework/mutable.py
pyappframework/ui/__init__.py
pyappframework/ui/artprovider.py
pyappframework/ui/attribute.py
pyappframework/ui/controls.py
pyappframework/ui/dialog.py
pyappframework/ui/menubar.py
pyappframework/ui/view.py
pyappframework/ui/window.py
pyappframework/ui/_controls/button.py
pyappframework/ui/_controls/checkbox.py
pyappframework/ui/_controls/choice.py
pyappframework/ui/_controls/collapsiblepanel.py
pyappframework/ui/_controls/control.py
pyappframework/ui/_controls/dataviewctrl.py
pyappframework/ui/_controls/gauge.py
pyappframework/ui/_controls/glcanvas.py
pyappframework/ui/_controls/infobar.py
pyappframework/ui/_controls/listbox.py
pyappframework/ui/_controls/notebook.py
pyappframework/ui/_controls/panel.py
pyappframework/ui/_controls/plot.py
pyappframework/ui/_controls/scrollablepanel.py
pyappframework/ui/_controls/searchctrl.py
pyappframework/ui/_controls/splitterwindow.py
pyappframework/ui/_controls/staticbitmap.py
pyappframework/ui/_controls/staticbox.py
pyappframework/ui/_controls/staticline.py
pyappframework/ui/_controls/statictext.py
pyappframework/ui/_controls/textctrl.py
pyappframework/ui/_controls/toolbar.py
pyappframework/ui/_controls/treectrl.py
pyappframework/ui/_controls/webview.py
pyappframework-0.0.dev0.dist-info/LICENSE
pyappframework-0.0.dev0.dist-info/METADATA
pyappframework-0.0.dev0.dist-info/WHEEL
pyappframework-0.0.dev0.dist-info/top_level.txt
pyappframework-0.0.dev0.dist-info/RECORD
