Metadata-Version: 2.1
Name: pyappframework
Version: 0.0.dev0
Summary: A small example package
Author-email: kms1212 <kms1212g@gmail.com>
License: BSD 3-Clause License
Project-URL: Homepage, https://github.com/kms1212/pyApplicationFramework
Project-URL: Issues, https://github.com/kms1212/pyApplicationFramework/issues
Keywords: gui,application,framework,wxwidgets,wxpython
Classifier: Development Status :: 2 - Pre-Alpha
Classifier: Programming Language :: Python :: 3
Classifier: License :: OSI Approved :: BSD License
Classifier: Operating System :: POSIX
Classifier: Operating System :: MacOS
Classifier: Operating System :: Microsoft :: Windows
Classifier: Framework :: Matplotlib
Classifier: Topic :: Software Development
Classifier: Topic :: Software Development :: Libraries :: Application Frameworks
Classifier: Topic :: Software Development :: User Interfaces
Classifier: Topic :: Software Development :: Widget Sets
Classifier: Topic :: Utilities
Classifier: Typing :: Typed
Requires-Python: >=3.9
License-File: LICENSE
Requires-Dist: wxPython >=4.1.0
Requires-Dist: typing-extensions >=4.0.0
Provides-Extra: matplotlib
Requires-Dist: matplotlib ; extra == 'matplotlib'
Provides-Extra: opengl
Requires-Dist: PyOpenGL ; extra == 'opengl'
